esco/__init__.py
esco/cv.py
esco/esco.json.gz
esco/esco_o.json.gz
esco/esco_s.json.gz
esco/ner.py
esco/sparql.py
esco/util.py
esco/vector.py
schemas/skills.oas3.yaml
sparql/nginx.conf
sparql/virtuoso.ini
sparql/virtuoso.sh
vocabularies/copy-here-the-esco-ttl-file
vocabularies/esco-padding.ttl
esco_playground-0.1.0.dist-info/LICENSE
esco_playground-0.1.0.dist-info/METADATA
esco_playground-0.1.0.dist-info/WHEEL
esco_playground-0.1.0.dist-info/top_level.txt
esco_playground-0.1.0.dist-info/RECORD
