Metadata-Version: 2.1
Name: esco_playground
Version: 0.1.0
License-File: LICENSE
Requires-Dist: pandas ==2.1.4
Requires-Dist: spacy ==3.7.2
Requires-Dist: spacy-transformers ==1.3.4
Requires-Dist: spacy-curated-transformers ==0.2.1
Requires-Dist: sparqlwrapper ==2.0.0
Requires-Dist: sentence-transformers ==2.2.2
Provides-Extra: dev
Requires-Dist: pytest ; extra == 'dev'
Requires-Dist: jupyter ; extra == 'dev'
Requires-Dist: langchain ==0.1.0 ; extra == 'dev'
Requires-Dist: langchain-community ==0.0.12 ; extra == 'dev'
Requires-Dist: qdrant-client ==1.7.0 ; extra == 'dev'
Requires-Dist: nltk ==3.8.1 ; extra == 'dev'
Requires-Dist: tiktoken ==0.5.2 ; extra == 'dev'
Requires-Dist: spacy-huggingface-hub ==0.0.10 ; extra == 'dev'
Provides-Extra: langchain
Requires-Dist: langchain ==0.1.0 ; extra == 'langchain'
Requires-Dist: langchain-community ==0.0.12 ; extra == 'langchain'
Requires-Dist: qdrant-client ==1.7.0 ; extra == 'langchain'
